RanCat-1.1.0.dist-info/DESCRIPTION.rst
RanCat-1.1.0.dist-info/METADATA
RanCat-1.1.0.dist-info/RECORD
RanCat-1.1.0.dist-info/WHEEL
RanCat-1.1.0.dist-info/metadata.json
RanCat-1.1.0.dist-info/top_level.txt
rancat/Handler.py
rancat/RanCat.py
rancat/__init__.py
rancat/conversions.py
