Metadata-Version: 2.0
Name: RanCat
Version: 1.1.0
Summary: A random string generator
Home-page: https://github.com/mattjegan/rancat
Author: Matthew Egan
Author-email: UNKNOWN
License: UNKNOWN
Platform: UNKNOWN
